hlsvdpropy/__init__.py
hlsvdpropy/hlsvd.py
hlsvdpropy/simple_test.py
hlsvdpropy-2.0.2.dist-info/LICENSE
hlsvdpropy-2.0.2.dist-info/METADATA
hlsvdpropy-2.0.2.dist-info/WHEEL
hlsvdpropy-2.0.2.dist-info/top_level.txt
hlsvdpropy-2.0.2.dist-info/RECORD
