Metadata-Version: 2.1
Name: hlsvdpropy
Version: 2.0.2
Summary: This is a 'pure Python' implementation of the HLSVDPRO package version 2.0.0. It fits time domain data to a model function that is a set of lorentzian decaying sinusoids using the state space approach.
Home-page: https://github.com/bsoher/hlsvdpropy
Author: Brian J. Soher
Author-email: bsoher@briansoher.com
Maintainer: Brian J. Soher
Maintainer-email: bsoher@briansoher.com
License: https://opensource.org/licenses/BSD-3-Clause
Keywords: svd,hlsvd,hlsvdpro,propack,time domain,fitting
Platform: Linux
Platform: OS X
Platform: Windows
Platform: POSIX
Classifier: Development Status :: 5 - Production/Stable
Classifier: Intended Audience :: Science/Research
Classifier: License :: OSI Approved :: BSD License
Classifier: Operating System :: MacOS :: MacOS X
Classifier: Operating System :: POSIX :: Linux
Classifier: Operating System :: Microsoft :: Windows
Classifier: Operating System :: Unix
License-File: LICENSE
Requires-Dist: setuptools
